[
	{"Name": "NEIGHBOR", "Acc":"earrings/earring_emerald", "Hair":"long_straight_skirt", "Tops":"sailor_bow", "Text": "Hi there! Welcome to ToastyTown!"},
	{"Name": "NEIGHBOR", "Acc":"earrings/earring_emerald", "Hair":"long_straight_skirt", "Tops":"sailor_bow", "Text": "I'm the mayor here! This town is the place for you to get toasty and relax."},
	{"Name": "NEIGHBOR", "Acc":"earrings/earring_emerald", "Hair":"long_straight_skirt", "Tops":"sailor_bow", "Text": "Have fun and explore this town of ours"},
	{"Name": "NEIGHBOR", "Acc":"earrings/earring_emerald", "Hair":"long_straight_skirt", "Tops":"sailor_bow", "Text": "If you have any questions, come find me!"}
]